<?xml version="1.0" encoding="utf-8" ?>
<dwsync>
<file name="add-framed-image.gif" server="ftp.terrasoft.x10.mx/public_html/etc/el/" local="128006780400000000" remote="129679131600000000" />
<file name="add-image.gif" server="ftp.terrasoft.x10.mx/public_html/etc/el/" local="128006780400000000" remote="129679131600000000" />
<file name="buttongrad.jpg" server="ftp.terrasoft.x10.mx/public_html/etc/el/" local="128006780380000000" remote="129679131600000000" />
<file name="font-color.gif" server="ftp.terrasoft.x10.mx/public_html/etc/el/" local="128006780380000000" remote="129679131600000000" />
<file name="font-size.gif" server="ftp.terrasoft.x10.mx/public_html/etc/el/" local="128006780400000000" remote="129679131600000000" />
<file name="font.gif" server="ftp.terrasoft.x10.mx/public_html/etc/el/" local="128006780380000000" remote="129679131600000000" />
<file name="footcell.jpg" server="ftp.terrasoft.x10.mx/public_html/etc/el/" local="128006780400000000" remote="129679131600000000" />
<file name="grad1.jpg" server="ftp.terrasoft.x10.mx/public_html/etc/el/" local="128050976200000000" remote="129679131600000000" />
<file name="grad2.jpg" server="ftp.terrasoft.x10.mx/public_html/etc/el/" local="128050976480000000" remote="129679131600000000" />
<file name="grad3.jpg" server="ftp.terrasoft.x10.mx/public_html/etc/el/" local="128047467360000000" remote="129679131600000000" />
<file name="headcell-small.jpg" server="ftp.terrasoft.x10.mx/public_html/etc/el/" local="128035391380000000" remote="129679131600000000" />
<file name="headcell.jpg" server="ftp.terrasoft.x10.mx/public_html/etc/el/" local="128037195900000000" remote="129679131600000000" />
<file name="headcell2.jpg" server="ftp.terrasoft.x10.mx/public_html/etc/el/" local="128006780400000000" remote="129679131600000000" />
<file name="header.jpg" server="ftp.terrasoft.x10.mx/public_html/etc/el/" local="129678985927229111" remote="129679131600000000" />
<file name="headerbg.jpg" server="ftp.terrasoft.x10.mx/public_html/etc/el/" local="128006780420000000" remote="129679131600000000" />
<file name="icon_cp.gif" server="ftp.terrasoft.x10.mx/public_html/etc/el/" local="128006780420000000" remote="129679131600000000" />
<file name="icon_editnews1.gif" server="ftp.terrasoft.x10.mx/public_html/etc/el/" local="128006780420000000" remote="129679131600000000" />
<file name="icon_editnews2.gif" server="ftp.terrasoft.x10.mx/public_html/etc/el/" local="128006780420000000" remote="129679131600000000" />
<file name="icon_folder.gif" server="ftp.terrasoft.x10.mx/public_html/etc/el/" local="128006780420000000" remote="129679131600000000" />
<file name="icon_home.gif" server="ftp.terrasoft.x10.mx/public_html/etc/el/" local="128006780420000000" remote="129679131600000000" />
<file name="icon_info.gif" server="ftp.terrasoft.x10.mx/public_html/etc/el/" local="128052434620000000" remote="129679131600000000" />
<file name="icon_login.gif" server="ftp.terrasoft.x10.mx/public_html/etc/el/" local="128006780440000000" remote="129679131600000000" />
<file name="icon_mini_folder.gif" server="ftp.terrasoft.x10.mx/public_html/etc/el/" local="128006780440000000" remote="129679131600000000" />
<file name="icon_mypictures.gif" server="ftp.terrasoft.x10.mx/public_html/etc/el/" local="128006780440000000" remote="129679131600000000" />
<file name="icon_picture.gif" server="ftp.terrasoft.x10.mx/public_html/etc/el/" local="128006780440000000" remote="129679131600000000" />
<file name="logo.jpg" server="ftp.terrasoft.x10.mx/public_html/etc/el/" local="129740823262717909" remote="129740862000000000" />
<file name="rss-google.gif" server="ftp.terrasoft.x10.mx/public_html/etc/el/" local="128006780440000000" remote="129679131600000000" />
<file name="rss-yahoo.gif" server="ftp.terrasoft.x10.mx/public_html/etc/el/" local="128006780440000000" remote="129679131600000000" />
<file name="rss.gif" server="ftp.terrasoft.x10.mx/public_html/etc/el/" local="128006780440000000" remote="129679131600000000" />
<file name="text-align-center.gif" server="ftp.terrasoft.x10.mx/public_html/etc/el/" local="128006780440000000" remote="129679131600000000" />
<file name="text-align-left.gif" server="ftp.terrasoft.x10.mx/public_html/etc/el/" local="128006780440000000" remote="129679131600000000" />
<file name="text-align-right.gif" server="ftp.terrasoft.x10.mx/public_html/etc/el/" local="128006780440000000" remote="129679131600000000" />
<file name="toolbar-bg.jpg" server="ftp.terrasoft.x10.mx/public_html/etc/el/" local="128006780460000000" remote="129679131600000000" />
<file name="toolbar-split.jpg" server="ftp.terrasoft.x10.mx/public_html/etc/el/" local="128122728920000000" remote="129679131600000000" />
<file name="toolbar-tab.jpg" server="ftp.terrasoft.x10.mx/public_html/etc/el/" local="128122746940000000" remote="129679131600000000" />
<file name="winfooter.jpg" server="ftp.terrasoft.x10.mx/public_html/etc/el/" local="128006780460000000" remote="129679131600000000" />
<file name="Thumbs.db" server="ftp.terrasoft.x10.mx/public_html/etc/el/" local="129740823301550130" remote="129740862000000000" />
</dwsync>